gym_miniworld/__init__.py
gym_miniworld/entity.py
gym_miniworld/math.py
gym_miniworld/miniworld.py
gym_miniworld/objmesh.py
gym_miniworld/opengl.py
gym_miniworld/params.py
gym_miniworld/random.py
gym_miniworld/utils.py
gym_miniworld/wrappers.py
gym_miniworld/envs/__init__.py
gym_miniworld/envs/collecthealth.py
gym_miniworld/envs/fourrooms.py
gym_miniworld/envs/hallway.py
gym_miniworld/envs/maze.py
gym_miniworld/envs/oneroom.py
gym_miniworld/envs/pickupobjs.py
gym_miniworld/envs/putnext.py
gym_miniworld/envs/remotebot.py
gym_miniworld/envs/roomobjs.py
gym_miniworld/envs/sidewalk.py
gym_miniworld/envs/simtorealgoto.py
gym_miniworld/envs/simtorealpush.py
gym_miniworld/envs/threerooms.py
gym_miniworld/envs/tmaze.py
gym_miniworld/envs/wallgap.py
gym_miniworld/envs/ymaze.py
gym_miniworld/meshes/ball.obj
gym_miniworld/meshes/ball_blue.mtl
gym_miniworld/meshes/ball_blue.obj
gym_miniworld/meshes/ball_green.mtl
gym_miniworld/meshes/ball_green.obj
gym_miniworld/meshes/ball_grey.mtl
gym_miniworld/meshes/ball_grey.obj
gym_miniworld/meshes/ball_purple.mtl
gym_miniworld/meshes/ball_purple.obj
gym_miniworld/meshes/ball_red.mtl
gym_miniworld/meshes/ball_red.obj
gym_miniworld/meshes/ball_yellow.mtl
gym_miniworld/meshes/ball_yellow.obj
gym_miniworld/meshes/barrel.mtl
gym_miniworld/meshes/barrel.obj
gym_miniworld/meshes/barrel.png
gym_miniworld/meshes/barrier.obj
gym_miniworld/meshes/barrier.png
gym_miniworld/meshes/building.obj
gym_miniworld/meshes/building.png
gym_miniworld/meshes/cone.obj
gym_miniworld/meshes/cone.png
gym_miniworld/meshes/doom_door.mtl
gym_miniworld/meshes/doom_door.obj
gym_miniworld/meshes/doom_door.png
gym_miniworld/meshes/duckie.obj
gym_miniworld/meshes/duckie.png
gym_miniworld/meshes/key.mtl
gym_miniworld/meshes/key.obj
gym_miniworld/meshes/key_blue.mtl
gym_miniworld/meshes/key_blue.obj
gym_miniworld/meshes/key_green.mtl
gym_miniworld/meshes/key_green.obj
gym_miniworld/meshes/key_grey.mtl
gym_miniworld/meshes/key_grey.obj
gym_miniworld/meshes/key_purple.mtl
gym_miniworld-2020.1.9.dist-info/LICENSE
gym_miniworld-2020.1.9.dist-info/METADATA
gym_miniworld-2020.1.9.dist-info/WHEEL
gym_miniworld-2020.1.9.dist-info/top_level.txt
gym_miniworld-2020.1.9.dist-info/RECORD
