Metadata-Version: 2.1
Name: gym-miniworld
Version: 2020.1.9
Summary: UNKNOWN
Home-page: UNKNOWN
Author: UNKNOWN
Author-email: UNKNOWN
License: UNKNOWN
Keywords: environment,agent,rl,openaigym,openai-gym,gym,robotics,3d
Platform: UNKNOWN
Requires-Dist: gym (>=0.9.0)
Requires-Dist: numpy (>=1.10.0)
Requires-Dist: pyglet
